bibliothekarios/__init__.py
bibliothekarios/entities.py
bibliothekarios-0.0.2.dist-info/licenses/LICENSE
bibliothekarios-0.0.2.dist-info/METADATA
bibliothekarios-0.0.2.dist-info/WHEEL
bibliothekarios-0.0.2.dist-info/top_level.txt
bibliothekarios-0.0.2.dist-info/RECORD
